eazyplotly/__init__.py
eazyplotly/constants.py
eazyplotly/eazyplotly.py
eazyplotly-0.5.0.dist-info/METADATA
eazyplotly-0.5.0.dist-info/WHEEL
eazyplotly-0.5.0.dist-info/top_level.txt
eazyplotly-0.5.0.dist-info/RECORD
